rechub/__init__.py
rechub/loss.py
rechub/parameters.py
rechub/test.py
rechub/train.py
rechub/model/__init__.py
rechub/model/deepfm.py
rechub/model/dssm.py
rechub/model/ncf.py
rechub/model/general/__init__.py
rechub/model/general/attention/__init__.py
rechub/model/general/attention/additive.py
rechub/model/general/predictor/__init__.py
rechub/model/general/predictor/dnn.py
rechub/model/general/predictor/dot.py
rechub/model/heterogeneous/__init__.py
rechub/model/heterogeneous/network.py
rechub/model/heterogeneous/aggregator/__init__.py
rechub/model/heterogeneous/aggregator/base.py
rechub/model/heterogeneous/aggregator/gat.py
rechub/model/heterogeneous/aggregator/gcn.py
rechub/model/heterogeneous/aggregator/lightgcn/__init__.py
rechub/model/heterogeneous/aggregator/lightgcn/lightgcn.py
rechub/model/heterogeneous/aggregator/lightgcn/lightgcn_conv.py
rechub/model/heterogeneous/aggregator/ngcf/__init__.py
rechub/model/heterogeneous/aggregator/ngcf/ngcf.py
rechub/model/heterogeneous/aggregator/ngcf/ngcf_conv.py
rechub/utils/__init__.py
rechub/utils/early_stop.py
rechub/utils/metrics.py
rechub/utils/other.py
rechub-0.0.5.dist-info/LICENSE
rechub-0.0.5.dist-info/METADATA
rechub-0.0.5.dist-info/WHEEL
rechub-0.0.5.dist-info/top_level.txt
rechub-0.0.5.dist-info/RECORD
