Metadata-Version: 2.1
Name: rechub
Version: 0.0.5
Summary: A package with implementations of some methods in recommendation
Home-page: https://github.com/yusanshi/RecHub
Author: yusanshi
Author-email: meet.leiyu@gmail.com
License: UNKNOWN
Project-URL: Bug Tracker, https://github.com/yusanshi/RecHub/issues
Platform: UNKNOWN
Classifier: Programming Language :: Python :: 3
Classifier: License :: OSI Approved :: MIT License
Classifier: Operating System :: POSIX :: Linux
Requires-Python: >=3.6
License-File: LICENSE
Requires-Dist: torch
Requires-Dist: pandas
Requires-Dist: numpy
Requires-Dist: scikit-learn
Requires-Dist: tensorboard
Requires-Dist: enlighten
Requires-Dist: coloredlogs
